CHANGES.rst
MANIFEST.in
README.rst
setup.py
django_admin_backend.egg-info/PKG-INFO
django_admin_backend.egg-info/SOURCES.txt
django_admin_backend.egg-info/dependency_links.txt
django_admin_backend.egg-info/not-zip-safe
django_admin_backend.egg-info/requires.txt
django_admin_backend.egg-info/top_level.txt
django_backend/__init__.py
django_backend/apps.py
django_backend/autoload.py
django_backend/compat.py
django_backend/group.py
django_backend/image_formats.py
django_backend/localstate.py
django_backend/models.py
django_backend/permissions.py
django_backend/sitebackend.py
django_backend/state.py
django_backend/widgets.py
django_backend/administration/__init__.py
django_backend/administration/backend.py
django_backend/administration/backends.py
django_backend/administration/views.py
django_backend/administration/templates/django_backend/administration/index.html
django_backend/administration/templates/django_backend/administration/password_change.html
django_backend/auth_backend/__init__.py
django_backend/auth_backend/backend.py
django_backend/auth_backend/models.py
django_backend/auth_backend/permissions.py
django_backend/backend/__init__.py
django_backend/backend/actions.py
django_backend/backend/ajax.py
django_backend/backend/columns.py
django_backend/backend/form_tabs.py
django_backend/backend/forms.py
django_backend/backend/inline_related.py
django_backend/backend/preview.py
django_backend/backend/renderable.py
django_backend/backend/urlname_helper.py
django_backend/backend/utils.py
django_backend/backend/base/__init__.py
django_backend/backend/base/backends.py
django_backend/backend/base/views/__init__.py
django_backend/backend/base/views/create.py
django_backend/backend/base/views/delete.py
django_backend/backend/base/views/edit.py
django_backend/backend/base/views/list.py
django_backend/backend/base/views/mixins.py
django_backend/backend/base/views/read.py
django_backend/backend/base/views/select.py
django_backend/backend/base/views/update.py
django_backend/backend/views/__init__.py
django_backend/backend/views/base.py
django_backend/backend/views/modelviews.py
django_backend/backend/views/permissions.py
django_backend/forms/__init__.py
django_backend/forms/fields.py
django_backend/forms/filterforms.py
