Metadata-Version: 1.1
Name: django-admin-backend
Version: 0.6.0
Summary: A replacement of django.contrib.admin
Home-page: https://github.com/team23/django-backend
Author: David Danier
Author-email: david.danier@team23.de
License: BSD licence, see LICENSE file
Platform: UNKNOWN
Classifier: Development Status :: 3 - Alpha
Classifier: Environment :: Web Environment
Classifier: Framework :: Django
Classifier: Framework :: Django :: 1.6
Classifier: Framework :: Django :: 1.8
Classifier: Intended Audience :: Developers
Classifier: License :: OSI Approved :: BSD License
Classifier: Natural Language :: English
Classifier: Programming Language :: Python
Classifier: Programming Language :: Python :: 2
Classifier: Programming Language :: Python :: 2.7
